README.txt
setup.cfg
setup.py
taskjuggler-gantt
taskjuggler-report
taskjuggler-timeshift
ez_setup/README.txt
ez_setup/__init__.py
taskjuggler_utils/__init__.py
taskjuggler_utils/parser.py
taskjuggler_utils.egg-info/PKG-INFO
taskjuggler_utils.egg-info/SOURCES.txt
taskjuggler_utils.egg-info/dependency_links.txt
taskjuggler_utils.egg-info/requires.txt
taskjuggler_utils.egg-info/top_level.txt
taskjuggler_utils.egg-info/zip-safe