Metadata-Version: 1.0
Name: taskjuggler-utils
Version: 0.1
Summary: Tools to help use "taskjuggler" without its GUI and produce nice reports.
Home-page: http://barbieri-playground.googlecode.com/svn/python/taskjuggler-utils/
Author: Gustavo Sverzut Barbieri
Author-email: barbieri@gmail.com
License: PSF
Keywords: taskjuggler helper scripts tools project management gantt
Platform: UNKNOWN
Classifier: Development Status :: 3 - Alpha
Classifier: Environment :: Console
Classifier: Intended Audience :: Information Technology
Classifier: License :: OSI Approved :: Python Software Foundation License
Classifier: Programming Language :: Python
Classifier: Topic :: Office/Business :: Scheduling
Classifier: Topic :: Scientific/Engineering :: Information Analysis
Classifier: Topic :: Text Processing :: Markup :: LaTeX
